{
  "isPromise": true,
  "volume": "Seeker.callSlowFind",
  "args": [
    {
      "pattern": "like a dog",
      "showMatchesOnly": true,
      "languages": [
        "pli",
        "en"
      ],
      "maxResults": 1000,
      "searchLang": "en",
      "maxDoc": 50,
      "minLang": 2,
      "matchHighlight": "<span class=\"ebt-matched\">$&</span>",
      "lang": "en",
      "types": [
        "root",
        "translation"
      ],
      "includeUnpublished": false
    }
  ],
  "value": {
    "lang": "en",
    "searchLang": "en",
    "minLang": 2,
    "maxDoc": 50,
    "maxResults": 1000,
    "pattern": "like a dog",
    "method": "phrase",
    "resultPattern": "\\blike a dog",
    "segsMatched": 8,
    "bilaraPaths": [
      "root/pli/ms/sutta/mn/mn57_root-pli-ms.json",
      "translation/en/sujato/sutta/mn/mn57_translation-en-sujato.json",
      "root/pli/ms/sutta/kn/thig/thig16.1_root-pli-ms.json",
      "translation/en/sujato/sutta/kn/thig/thig16.1_translation-en-sujato.json",
      "translation/en/soma/sutta/kn/thig/thig16.1_translation-en-soma.json",
      "root/pli/ms/sutta/dn/dn24_root-pli-ms.json",
      "translation/en/sujato/sutta/dn/dn24_translation-en-sujato.json",
      "root/pli/ms/sutta/kn/thig/thig16.1_root-pli-ms.json",
      "translation/en/sujato/sutta/kn/thig/thig16.1_translation-en-sujato.json",
      "translation/en/soma/sutta/kn/thig/thig16.1_translation-en-soma.json"
    ],
    "suttaRefs": [
      "mn57/en/sujato",
      "thig16.1/en/sujato",
      "dn24/en/sujato",
      "thig16.1/en/soma"
    ],
    "mlDocs": [
      {
        "bilaraPaths": [
          "root/pli/ms/sutta/mn/mn57_root-pli-ms.json",
          "translation/en/sujato/sutta/mn/mn57_translation-en-sujato.json"
        ],
        "author_uid": "sujato",
        "type": "translation",
        "category": "sutta",
        "sutta_uid": "mn57",
        "lang": "en",
        "segMap": {
          "mn57:0.2": {
            "scid": "mn57:0.2",
            "pli": "Kukkuravatikasutta ",
            "en": "The Ascetic Who Behaved <span class=\"ebt-matched\">Like a Dog</span> ",
            "matched": true
          },
          "mn57:2.1": {
            "scid": "mn57:2.1",
            "pli": "Atha kho puṇṇo ca koliyaputto govatiko acelo ca seniyo kukkuravatiko yena bhagavā tenupasaṅkamiṁsu; upasaṅkamitvā puṇṇo koliyaputto govatiko bhagavantaṁ abhivādetvā ekamantaṁ nisīdi. Acelo pana seniyo kukkuravatiko bhagavatā saddhiṁ sammodi. Sammodanīyaṁ kathaṁ sāraṇīyaṁ vītisāretvā kukkurova palikujjitvā ekamantaṁ nisīdi. ",
            "en": "Then Puṇṇa Koliyaputta, who had taken a vow to behave like a cow, and Seniya, a naked ascetic who had taken a vow to behave <span class=\"ebt-matched\">like a dog</span>, went to see the Buddha. Puṇṇa bowed to the Buddha and sat down to one side, while Seniya exchanged greetings and polite conversation with him before sitting down to one side curled up <span class=\"ebt-matched\">like a dog</span>. ",
            "matched": true
          },
          "mn57:2.4": {
            "scid": "mn57:2.4",
            "pli": "Tassa taṁ kukkuravataṁ dīgharattaṁ samattaṁ samādinnaṁ. ",
            "en": "For a long time he has undertaken that observance to behave <span class=\"ebt-matched\">like a dog</span>. ",
            "matched": true
          },
          "mn57:2.10": {
            "scid": "mn57:2.10",
            "pli": "Tassa taṁ kukkuravataṁ dīgharattaṁ samattaṁ samādinnaṁ. ",
            "en": "For a long time he has undertaken that observance to behave <span class=\"ebt-matched\">like a dog</span>. ",
            "matched": true
          },
          "mn57:4.6": {
            "scid": "mn57:4.6",
            "pli": "api ca me idaṁ, bhante, kukkuravataṁ dīgharattaṁ samattaṁ samādinnaṁ. ",
            "en": "But, sir, for a long time I have undertaken this observance to behave <span class=\"ebt-matched\">like a dog</span>. ",
            "matched": true
          }
        },
        "score": 5.044,
        "hyphen": "­",
        "maxWord": 30,
        "minWord": 5,
        "title": "Middle Discourses 57\nThe Ascetic Who Behaved Like a Dog",
        "segsMatched": 5,
        "langSegs": {
          "pli": 114,
          "en": 113
        }
      },
      {
        "bilaraPaths": [
          "root/pli/ms/sutta/kn/thig/thig16.1_root-pli-ms.json",
          "translation/en/sujato/sutta/kn/thig/thig16.1_translation-en-sujato.json",
          "translation/en/soma/sutta/kn/thig/thig16.1_translation-en-soma.json"
        ],
        "author_uid": "sujato",
        "type": "translation",
        "category": "sutta",
        "sutta_uid": "thig16.1",
        "lang": "en",
        "segMap": {
          "thig16.1:62.2": {
            "scid": "thig16.1:62.2",
            "pli": "Tāva sunakhova saṅkhalābaddho; ",
            "en": "You’re <span class=\"ebt-matched\">like a dog</span> fixed to a chain:",
            "matched": true
          }
        },
        "score": 1.003,
        "hyphen": "­",
        "maxWord": 30,
        "minWord": 5,
        "title": "Verses of the Senior Nuns 16.1\nThe Great Book\nSumedhā",
        "segsMatched": 1,
        "langSegs": {
          "pli": 311,
          "en": 306
        }
      },
      {
        "bilaraPaths": [
          "root/pli/ms/sutta/kn/thig/thig16.1_root-pli-ms.json",
          "translation/en/sujato/sutta/kn/thig/thig16.1_translation-en-sujato.json",
          "translation/en/soma/sutta/kn/thig/thig16.1_translation-en-soma.json"
        ],
        "author_uid": "sujato",
        "type": "translation",
        "category": "sutta",
        "sutta_uid": "thig16.1",
        "lang": "en",
        "segMap": {
          "thig16.1:62.2": {
            "scid": "thig16.1:62.2",
            "pli": "Tāva sunakhova saṅkhalābaddho; ",
            "en": "You’re <span class=\"ebt-matched\">like a dog</span> fixed to a chain:",
            "matched": true
          }
        },
        "score": 1.003,
        "hyphen": "­",
        "maxWord": 30,
        "minWord": 5,
        "title": "Verses of the Senior Nuns 16.1\nThe Great Book\nSumedhā",
        "segsMatched": 1,
        "langSegs": {
          "pli": 311,
          "en": 306
        }
      },
      {
        "bilaraPaths": [
          "root/pli/ms/sutta/dn/dn24_root-pli-ms.json",
          "translation/en/sujato/sutta/dn/dn24_translation-en-sujato.json"
        ],
        "author_uid": "sujato",
        "type": "translation",
        "category": "sutta",
        "sutta_uid": "dn24",
        "lang": "en",
        "segMap": {
          "dn24:1.7.3": {
            "scid": "dn24:1.7.3",
            "pli": "Tena kho pana samayena acelo korakkhattiyo kukkuravatiko catukkuṇḍiko chamānikiṇṇaṁ bhakkhasaṁ mukheneva khādati, mukheneva bhuñjati. ",
            "en": "Now at that time the naked ascetic Korakkhattiya had taken a vow to behave <span class=\"ebt-matched\">like a dog</span>. When food is tossed on the ground, he gets down on all fours, eating and devouring it just with his mouth. ",
            "matched": true
          }
        },
        "score": 1.002,
        "hyphen": "­",
        "maxWord": 30,
        "minWord": 5,
        "title": "Long Discourses 24\nAbout Pāṭikaputta",
        "segsMatched": 1,
        "langSegs": {
          "pli": 581,
          "en": 580
        }
      }
    ]
  }
}