{
  "isPromise": true,
  "volume": "Seeker.callSlowFind",
  "args": [
    {
      "author": "sujato",
      "docLang": "en",
      "docAuthor": "sujato",
      "includeUnpublished": false,
      "lang": "en",
      "langAuthor": "sujato",
      "languages": [
        "pli",
        "en",
        "ref"
      ],
      "matchHighlight": "<span class=\"ebt-matched\">$&</span>",
      "maxDoc": 50,
      "maxResults": 1000,
      "minLang": 2,
      "pattern": "three characteristics",
      "refAuthor": "sujato",
      "refLang": "en",
      "searchLang": "en",
      "searchAuthor": "sujato",
      "showMatchesOnly": true,
      "trilingual": false,
      "types": [
        "root",
        "translation"
      ]
    }
  ],
  "value": {
    "author": "sujato",
    "lang": "en",
    "searchLang": "en",
    "minLang": 2,
    "maxDoc": 50,
    "maxResults": 1000,
    "pattern": "three characteristics",
    "method": "phrase",
    "resultPattern": "\\bthree characteristics",
    "segsMatched": 10,
    "bilaraPaths": [
      "root/pli/ms/sutta/an/an3/an3.47_root-pli-ms.json",
      "translation/en/sujato/sutta/an/an3/an3.47_translation-en-sujato.json",
      "root/pli/ms/sutta/an/an3/an3.3_root-pli-ms.json",
      "translation/en/sujato/sutta/an/an3/an3.3_translation-en-sujato.json",
      "root/pli/ms/sutta/mn/mn129_root-pli-ms.json",
      "translation/en/sujato/sutta/mn/mn129_translation-en-sujato.json"
    ],
    "suttaRefs": [
      "an3.47/en/sujato",
      "an3.3/en/sujato",
      "mn129/en/sujato"
    ],
    "mlDocs": [
      {
        "author": "Bhikkhu Sujato",
        "segMap": {
          "an3.47:1.1": {
            "scid": "an3.47:1.1",
            "pli": "“Tīṇimāni, bhikkhave, saṅkhatassa saṅkhatalakkhaṇāni. ",
            "en": "“Mendicants, the conditioned has these <span class=\"ebt-matched\">three characteristics</span>. ",
            "matched": true
          },
          "an3.47:1.4": {
            "scid": "an3.47:1.4",
            "pli": "Imāni kho, bhikkhave, tīṇi saṅkhatassa saṅkhatalakkhaṇānī”ti. ",
            "en": "These are the <span class=\"ebt-matched\">three characteristics</span> of the conditioned.” ",
            "matched": true
          },
          "an3.47:2.1": {
            "scid": "an3.47:2.1",
            "pli": "“Tīṇimāni, bhikkhave, asaṅkhatassa asaṅkhatalakkhaṇāni. ",
            "en": "“The unconditioned has these <span class=\"ebt-matched\">three characteristics</span>. ",
            "matched": true
          },
          "an3.47:2.4": {
            "scid": "an3.47:2.4",
            "pli": "Imāni kho, bhikkhave, tīṇi asaṅkhatassa asaṅkhatalakkhaṇānī”ti. ",
            "en": "These are the <span class=\"ebt-matched\">three characteristics</span> of the unconditioned.” ",
            "matched": true
          }
        },
        "author_uid": "sujato",
        "bilaraPaths": [
          "root/pli/ms/sutta/an/an3/an3.47_root-pli-ms.json",
          "translation/en/sujato/sutta/an/an3/an3.47_translation-en-sujato.json"
        ],
        "category": "sutta",
        "footer": "<a href=\"https://suttacentral.net/licensing\">Creative Commons Zero (CC0 1.0 Universal)</a>",
        "hyphen": "­",
        "lang": "en",
        "langSegs": {
          "pli": 14,
          "en": 13
        },
        "maxWord": 30,
        "minWord": 5,
        "score": 4.286,
        "segsMatched": 4,
        "sutta_uid": "an3.47",
        "title": "Numbered Discourses 3.47\n5. The Lesser Chapter\nCharacteristics of the Conditioned",
        "type": "translation"
      },
      {
        "author": "Bhikkhu Sujato",
        "segMap": {
          "an3.3:1.1": {
            "scid": "an3.3:1.1",
            "pli": "“Tīṇimāni, bhikkhave, bālassa bālalakkhaṇāni bālanimittāni bālāpadānāni. ",
            "en": "“There are these <span class=\"ebt-matched\">three characteristics</span>, signs, and manifestations of a fool. ",
            "matched": true
          },
          "an3.3:1.8": {
            "scid": "an3.3:1.8",
            "pli": "Imāni kho, bhikkhave, tīṇi bālassa bālalakkhaṇāni bālanimittāni bālāpadānāni. ",
            "en": "These are the <span class=\"ebt-matched\">three characteristics</span>, signs, and manifestations of a fool. ",
            "matched": true
          },
          "an3.3:2.1": {
            "scid": "an3.3:2.1",
            "pli": "Tīṇimāni, bhikkhave, paṇḍitassa paṇḍitalakkhaṇāni paṇḍitanimittāni paṇḍitāpadānāni. ",
            "en": "There are these <span class=\"ebt-matched\">three characteristics</span>, signs, and manifestations of an astute person. ",
            "matched": true
          },
          "an3.3:2.8": {
            "scid": "an3.3:2.8",
            "pli": "Imāni kho, bhikkhave, tīṇi paṇḍitassa paṇḍitalakkhaṇāni paṇḍitanimittāni paṇḍitāpadānāni. ",
            "en": "These are the <span class=\"ebt-matched\">three characteristics</span>, signs, and manifestations of an astute person. ",
            "matched": true
          }
        },
        "author_uid": "sujato",
        "bilaraPaths": [
          "root/pli/ms/sutta/an/an3/an3.3_root-pli-ms.json",
          "translation/en/sujato/sutta/an/an3/an3.3_translation-en-sujato.json"
        ],
        "category": "sutta",
        "footer": "<a href=\"https://suttacentral.net/licensing\">Creative Commons Zero (CC0 1.0 Universal)</a>",
        "hyphen": "­",
        "lang": "en",
        "langSegs": {
          "pli": 21,
          "en": 20
        },
        "maxWord": 30,
        "minWord": 5,
        "score": 4.19,
        "segsMatched": 4,
        "sutta_uid": "an3.3",
        "title": "Numbered Discourses 3.3\n1. Fools\nThinking",
        "type": "translation"
      },
      {
        "author": "Bhikkhu Sujato",
        "segMap": {
          "mn129:2.1": {
            "scid": "mn129:2.1",
            "pli": "“Tīṇimāni, bhikkhave, bālassa bālalakkhaṇāni bālanimittāni bālāpadānāni. ",
            "en": "“These are the <span class=\"ebt-matched\">three characteristics</span>, signs, and manifestations of a fool. ",
            "matched": true
          },
          "mn129:27.1": {
            "scid": "mn129:27.1",
            "pli": "Tīṇimāni, bhikkhave, paṇḍitassa paṇḍitalakkhaṇāni paṇḍitanimittāni paṇḍitāpadānāni. ",
            "en": "There are these <span class=\"ebt-matched\">three characteristics</span>, signs, and manifestations of an astute person. ",
            "matched": true
          }
        },
        "author_uid": "sujato",
        "bilaraPaths": [
          "root/pli/ms/sutta/mn/mn129_root-pli-ms.json",
          "translation/en/sujato/sutta/mn/mn129_translation-en-sujato.json"
        ],
        "category": "sutta",
        "footer": "<a href=\"https://suttacentral.net/licensing\">Creative Commons Zero (CC0 1.0 Universal)</a>",
        "hyphen": "­",
        "lang": "en",
        "langSegs": {
          "pli": 303,
          "en": 302
        },
        "maxWord": 30,
        "minWord": 5,
        "score": 2.007,
        "segsMatched": 2,
        "sutta_uid": "mn129",
        "title": "Middle Discourses 129\nThe Foolish and the Astute",
        "type": "translation"
      }
    ],
    "refLang": "en",
    "refAuthor": "sujato",
    "docLang": "en",
    "docAuthor": "sujato"
  }
}