{
  "isPromise": true,
  "volume": "Seeker.callSlowFind",
  "args": [
    {
      "author": "sujato",
      "docLang": "en",
      "docAuthor": "sujato",
      "includeUnpublished": false,
      "lang": "en",
      "langAuthor": "sujato",
      "languages": [
        "pli",
        "en",
        "ref"
      ],
      "matchHighlight": "<span class=\"ebt-matched\">$&</span>",
      "maxDoc": 50,
      "maxResults": 1000,
      "minLang": 2,
      "pattern": "aware of the situation",
      "refAuthor": "sujato",
      "refLang": "en",
      "searchLang": "en",
      "searchAuthor": "sujato",
      "showMatchesOnly": true,
      "trilingual": false,
      "types": [
        "root",
        "translation"
      ]
    }
  ],
  "value": {
    "author": "sujato",
    "lang": "en",
    "searchLang": "en",
    "minLang": 2,
    "maxDoc": 50,
    "maxResults": 1000,
    "pattern": "aware of the situation",
    "method": "phrase",
    "resultPattern": "\\baware of the situation",
    "segsMatched": 21,
    "bilaraPaths": [
      "root/pli/ms/sutta/mn/mn122_root-pli-ms.json",
      "translation/en/sujato/sutta/mn/mn122_translation-en-sujato.json",
      "root/pli/ms/sutta/an/an7/an7.49_root-pli-ms.json",
      "translation/en/sujato/sutta/an/an7/an7.49_translation-en-sujato.json",
      "root/pli/ms/sutta/an/an8/an8.9_root-pli-ms.json",
      "translation/en/sujato/sutta/an/an8/an8.9_translation-en-sujato.json"
    ],
    "suttaRefs": [
      "mn122/en/sujato",
      "an7.49/en/sujato",
      "an8.9/en/sujato"
    ],
    "mlDocs": [
      {
        "author": "Bhikkhu Sujato",
        "segMap": {
          "mn122:9.5": {
            "scid": "mn122:9.5",
            "pli": "Itiha tattha sampajāno hoti. ",
            "en": "In this way they are <span class=\"ebt-matched\">aware of the situation</span>. ",
            "matched": true
          },
          "mn122:9.12": {
            "scid": "mn122:9.12",
            "pli": "Itiha tattha sampajāno hoti. ",
            "en": "In this way they are <span class=\"ebt-matched\">aware of the situation</span>. ",
            "matched": true
          },
          "mn122:10.6": {
            "scid": "mn122:10.6",
            "pli": "Itiha tattha sampajāno hoti. ",
            "en": "In this way they are <span class=\"ebt-matched\">aware of the situation</span>. ",
            "matched": true
          },
          "mn122:10.13": {
            "scid": "mn122:10.13",
            "pli": "Itiha tattha sampajāno hoti. ",
            "en": "In this way they are <span class=\"ebt-matched\">aware of the situation</span>. ",
            "matched": true
          },
          "mn122:11.3": {
            "scid": "mn122:11.3",
            "pli": "Itiha tattha sampajāno hoti. ",
            "en": "In this way they are <span class=\"ebt-matched\">aware of the situation</span>. ",
            "matched": true
          },
          "mn122:11.6": {
            "scid": "mn122:11.6",
            "pli": "Itiha tattha sampajāno hoti. ",
            "en": "In this way they are <span class=\"ebt-matched\">aware of the situation</span>. ",
            "matched": true
          },
          "mn122:11.9": {
            "scid": "mn122:11.9",
            "pli": "Itiha tattha sampajāno hoti. ",
            "en": "In this way they are <span class=\"ebt-matched\">aware of the situation</span>. ",
            "matched": true
          },
          "mn122:11.12": {
            "scid": "mn122:11.12",
            "pli": "Itiha tattha sampajāno hoti. ",
            "en": "In this way they are <span class=\"ebt-matched\">aware of the situation</span>. ",
            "matched": true
          },
          "mn122:12.3": {
            "scid": "mn122:12.3",
            "pli": "Itiha tattha sampajāno hoti. ",
            "en": "In this way they are <span class=\"ebt-matched\">aware of the situation</span>. ",
            "matched": true
          },
          "mn122:12.5": {
            "scid": "mn122:12.5",
            "pli": "Itiha tattha sampajāno hoti. ",
            "en": "In this way they are <span class=\"ebt-matched\">aware of the situation</span>. ",
            "matched": true
          },
          "mn122:13.3": {
            "scid": "mn122:13.3",
            "pli": "Itiha tattha sampajāno hoti. ",
            "en": "In this way they are <span class=\"ebt-matched\">aware of the situation</span>. ",
            "matched": true
          },
          "mn122:13.5": {
            "scid": "mn122:13.5",
            "pli": "Itiha tattha sampajāno hoti. ",
            "en": "In this way they are <span class=\"ebt-matched\">aware of the situation</span>. ",
            "matched": true
          },
          "mn122:15.7": {
            "scid": "mn122:15.7",
            "pli": "Itiha tattha sampajāno hoti. ",
            "en": "In this way they are <span class=\"ebt-matched\">aware of the situation</span>. ",
            "matched": true
          },
          "mn122:15.12": {
            "scid": "mn122:15.12",
            "pli": "Itiha tattha sampajāno hoti. ",
            "en": "In this way they are <span class=\"ebt-matched\">aware of the situation</span>. ",
            "matched": true
          },
          "mn122:17.4": {
            "scid": "mn122:17.4",
            "pli": "Itiha tattha sampajāno hoti. ",
            "en": "In this way they are <span class=\"ebt-matched\">aware of the situation</span>. ",
            "matched": true
          }
        },
        "author_uid": "sujato",
        "bilaraPaths": [
          "root/pli/ms/sutta/mn/mn122_root-pli-ms.json",
          "translation/en/sujato/sutta/mn/mn122_translation-en-sujato.json"
        ],
        "category": "sutta",
        "footer": "<a href=\"https://suttacentral.net/licensing\">SuttaCentral</a>",
        "hyphen": "­",
        "lang": "en",
        "langSegs": {
          "pli": 172,
          "en": 171
        },
        "maxWord": 30,
        "minWord": 5,
        "score": 15.087,
        "segsMatched": 15,
        "sutta_uid": "mn122",
        "title": "Middle Discourses 122\nThe Longer Discourse on Emptiness",
        "type": "translation"
      },
      {
        "author": "Bhikkhu Sujato",
        "segMap": {
          "an7.49:3.3": {
            "scid": "an7.49:3.3",
            "pli": "Itiha tattha sampajāno hoti. ",
            "en": "In this way they are <span class=\"ebt-matched\">aware of the situation</span>. ",
            "matched": true
          },
          "an7.49:3.6": {
            "scid": "an7.49:3.6",
            "pli": "Itiha tattha sampajāno hoti. ",
            "en": "In this way they are <span class=\"ebt-matched\">aware of the situation</span>. ",
            "matched": true
          },
          "an7.49:15.3": {
            "scid": "an7.49:15.3",
            "pli": "Itiha tattha sampajāno hoti. ",
            "en": "In this way they are <span class=\"ebt-matched\">aware of the situation</span>. ",
            "matched": true
          },
          "an7.49:16.3": {
            "scid": "an7.49:16.3",
            "pli": "Itiha tattha sampajāno hoti. ",
            "en": "In this way they are <span class=\"ebt-matched\">aware of the situation</span>. ",
            "matched": true
          }
        },
        "author_uid": "sujato",
        "bilaraPaths": [
          "root/pli/ms/sutta/an/an7/an7.49_root-pli-ms.json",
          "translation/en/sujato/sutta/an/an7/an7.49_translation-en-sujato.json"
        ],
        "category": "sutta",
        "footer": "<a href=\"https://suttacentral.net/licensing\">SuttaCentral</a>",
        "hyphen": "­",
        "lang": "en",
        "langSegs": {
          "pli": 94,
          "en": 93
        },
        "maxWord": 30,
        "minWord": 5,
        "score": 4.043,
        "segsMatched": 4,
        "sutta_uid": "an7.49",
        "title": "Numbered Discourses 7.49\n5. A Great Sacrifice\nPerceptions in Detail",
        "type": "translation"
      },
      {
        "author": "Bhikkhu Sujato",
        "segMap": {
          "an8.9:1.9": {
            "scid": "an8.9:1.9",
            "pli": "Itiha tattha sampajāno hoti. ",
            "en": "In this way he’s <span class=\"ebt-matched\">aware of the situation</span>. ",
            "matched": true
          },
          "an8.9:2.8": {
            "scid": "an8.9:2.8",
            "pli": "Itiha tattha sampajāno hoti. ",
            "en": "In this way he’s <span class=\"ebt-matched\">aware of the situation</span>. ",
            "matched": true
          }
        },
        "author_uid": "sujato",
        "bilaraPaths": [
          "root/pli/ms/sutta/an/an8/an8.9_root-pli-ms.json",
          "translation/en/sujato/sutta/an/an8/an8.9_translation-en-sujato.json"
        ],
        "category": "sutta",
        "footer": "<a href=\"https://suttacentral.net/licensing\">SuttaCentral</a>",
        "hyphen": "­",
        "lang": "en",
        "langSegs": {
          "pli": 38,
          "en": 37
        },
        "maxWord": 30,
        "minWord": 5,
        "score": 2.053,
        "segsMatched": 2,
        "sutta_uid": "an8.9",
        "title": "Numbered Discourses 8.9\n1. Love\nNanda",
        "type": "translation"
      }
    ],
    "refLang": "en",
    "refAuthor": "sujato",
    "docLang": "en",
    "docAuthor": "sujato"
  }
}