{
  "isPromise": true,
  "volume": "Seeker.callSlowFind",
  "args": [
    {
      "pattern": "wahrnehmung der unattraktiven natur",
      "showMatchesOnly": true,
      "languages": [
        "pli",
        "en",
        "de"
      ],
      "maxResults": 1000,
      "searchLang": "de",
      "maxDoc": 50,
      "minLang": 3,
      "matchHighlight": "<span class=\"ebt-matched\">$&</span>",
      "lang": "de",
      "types": [
        "root",
        "translation"
      ],
      "includeUnpublished": false
    }
  ],
  "value": {
    "lang": "de",
    "searchLang": "de",
    "minLang": 3,
    "maxDoc": 50,
    "maxResults": 1000,
    "pattern": "wahrnehmung der unattraktiven natur",
    "method": "phrase",
    "resultPattern": "\\bwahrnehmung der unattraktiven natur",
    "segsMatched": 0,
    "bilaraPaths": [],
    "suttaRefs": [],
    "mlDocs": []
  }
}